mvlearn/__init__.py
mvlearn/cluster/__init__.py
mvlearn/cluster/base.py
mvlearn/cluster/mv_coreg_spectral.py
mvlearn/cluster/mv_kmeans.py
mvlearn/cluster/mv_spectral.py
mvlearn/cluster/mv_spherical_kmeans.py
mvlearn/compose/__init__.py
mvlearn/compose/merge.py
mvlearn/compose/random_gaussian_projection.py
mvlearn/compose/rsm.py
mvlearn/compose/split.py
mvlearn/compose/utils.py
mvlearn/compose/wrap.py
mvlearn/datasets/__init__.py
mvlearn/datasets/factor_model.py
mvlearn/datasets/gaussian_mixture.py
mvlearn/datasets/nutrimouse.py
mvlearn/datasets/uci_multifeature.py
mvlearn/datasets/UCImultifeature/mfeat-fac.csv
mvlearn/datasets/UCImultifeature/mfeat-fou.csv
mvlearn/datasets/UCImultifeature/mfeat-kar.csv
mvlearn/datasets/UCImultifeature/mfeat-mor.csv
mvlearn/datasets/UCImultifeature/mfeat-pix.csv
mvlearn/datasets/UCImultifeature/mfeat-zer.csv
mvlearn/datasets/nutrimouse/diet.csv
mvlearn/datasets/nutrimouse/gene.csv
mvlearn/datasets/nutrimouse/genotype.csv
mvlearn/datasets/nutrimouse/lipid.csv
mvlearn/decomposition/__init__.py
mvlearn/decomposition/ajive.py
mvlearn/decomposition/base.py
mvlearn/decomposition/groupica.py
mvlearn/decomposition/grouppca.py
mvlearn/decomposition/multiviewica.py
mvlearn/embed/__init__.py
mvlearn/embed/base.py
mvlearn/embed/cca.py
mvlearn/embed/dcca.py
mvlearn/embed/gcca.py
mvlearn/embed/kmcca.py
mvlearn/embed/mcca.py
mvlearn/embed/mvmds.py
mvlearn/embed/splitae.py
mvlearn/embed/utils.py
mvlearn/model_selection/__init__.py
mvlearn/model_selection/split.py
mvlearn/model_selection/validation.py
mvlearn/plotting/__init__.py
mvlearn/plotting/plot.py
mvlearn/semi_supervised/__init__.py
mvlearn/semi_supervised/base.py
mvlearn/semi_supervised/ctclassifier.py
mvlearn/semi_supervised/ctregression.py
mvlearn/utils/__init__.py
mvlearn/utils/_testing.py
mvlearn/utils/linalg.py
mvlearn/utils/utils.py
tests/__init__.py
tests/test_basectestimator.py
tests/test_baseembed.py
tests/test_ctclassifier.py
tests/test_ctregressor.py
tests/test_utils.py
mvlearn-0.5.0.dist-info/LICENSE
mvlearn-0.5.0.dist-info/METADATA
mvlearn-0.5.0.dist-info/WHEEL
mvlearn-0.5.0.dist-info/top_level.txt
mvlearn-0.5.0.dist-info/RECORD
