Metadata-Version: 2.1
Name: mvlearn
Version: 0.5.0
Summary: A set of python modules for multiview learning
Home-page: https://github.com/mvlearn/mvlearn
Author: ('Richard Guo', 'Ronan Perry', 'Gavin Mischler', 'Theo Lee', 'Alexander Chang', 'Arman Koul', 'Cameron Franz', 'Alexandre Gramfort', 'Hugo Richard', 'Pierre Ablin', 'Iain Carmichael')
Author-email: rflperry@gmail.com
License: MIT
Project-URL: Documentation, https://mvlearn.github.io
Project-URL: Source, https://github.com/mvlearn/mvlearn
Project-URL: Tracker, https://github.com/mvlearn/mvlearn/issues/
Platform: UNKNOWN
Classifier: Development Status :: 3 - Alpha
Classifier: Intended Audience :: Science/Research
Classifier: Topic :: Scientific/Engineering :: Mathematics
Classifier: License :: OSI Approved :: MIT License
Classifier: Programming Language :: Python :: 3
Classifier: Programming Language :: Python :: 3.6
Classifier: Programming Language :: Python :: 3.7
Classifier: Programming Language :: Python :: 3.8
Provides-Extra: torch
Provides-Extra: multiviewica
License-File: LICENSE
